README-public-pypi.md
cisco_radkit_genie-1.9.2.dist-info/METADATA
cisco_radkit_genie-1.9.2.dist-info/WHEEL
cisco_radkit_genie-1.9.2.dist-info/entry_points.txt
cisco_radkit_genie-1.9.2.dist-info/licenses/LICENSE.md
radkit_genie/LICENSE.html
radkit_genie/LICENSE.md
radkit_genie/__init__.py
radkit_genie/api.py
radkit_genie/devices.py
radkit_genie/diff.py
radkit_genie/exceptions.py
radkit_genie/fingerprint.py
radkit_genie/learn.py
radkit_genie/parse.py
radkit_genie/py.typed
radkit_genie/settings.py
radkit_genie/utils.py
radkit_genie/version.py
cisco_radkit_genie-1.9.2.dist-info/RECORD
