Metadata-Version: 2.1
Name: cisco_radkit_genie
Version: 1.9.2
Summary: Cisco RADKit Genie Parsers
Keywords: cisco,remote,automation
Author-Email: "Cisco Systems Inc." <radkit@cisco.com>
License: Cisco Remote Automation Development Kit (RADKit) -- Copyright (c) 2018-2025 by Cisco Systems, Inc.
Classifier: Development Status :: 5 - Production/Stable
Classifier: Development Status :: 6 - Mature
Classifier: Intended Audience :: Developers
Classifier: Intended Audience :: Information Technology
Classifier: Intended Audience :: System Administrators
Classifier: Intended Audience :: Telecommunications Industry
Classifier: License :: Other/Proprietary License
Classifier: Operating System :: MacOS
Classifier: Operating System :: Microsoft :: Windows
Classifier: Operating System :: POSIX :: Linux
Classifier: Programming Language :: Python :: 3 :: Only
Classifier: Programming Language :: Python :: 3.10
Classifier: Programming Language :: Python :: 3.11
Classifier: Programming Language :: Python :: 3.12
Classifier: Programming Language :: Python :: 3.13
Classifier: Programming Language :: Python :: Implementation :: CPython
Classifier: Topic :: System :: Systems Administration
Project-URL: HomePage, https://radkit.cisco.com
Project-URL: Documentation, https://radkit.cisco.com/docs/index.html
Requires-Python: <3.14,>=3.10
Requires-Dist: cisco_radkit_client==1.9.2
Requires-Dist: cisco_radkit_common==1.9.2
Requires-Dist: pyats>=24.10; python_version < "3.13"
Requires-Dist: pyats>=25.1; python_version >= "3.13"
Requires-Dist: genie>=24.10; python_version < "3.13"
Requires-Dist: genie>=25.1; python_version >= "3.13"
Requires-Dist: yang.connector>=24.10; python_version < "3.13"
Requires-Dist: yang.connector>=25.1; python_version >= "3.13"
